setup.py
i3visiotools/__init__.py
i3visiotools/benchmark.py
i3visiotools/browser.py
i3visiotools/config_api_keys.py
i3visiotools/config_credentials.py
i3visiotools/credentials.py
i3visiotools/export.py
i3visiotools/general.py
i3visiotools/logger.py
i3visiotools.egg-info/PKG-INFO
i3visiotools.egg-info/SOURCES.txt
i3visiotools.egg-info/dependency_links.txt
i3visiotools.egg-info/requires.txt
i3visiotools.egg-info/top_level.txt
i3visiotools/apify/__init__.py
i3visiotools/apify/blockchain.py
i3visiotools/apify/haveibeenpwned.py
i3visiotools/apify/ip_api.py
i3visiotools/apify/md5crack.py
i3visiotools/apify/skype.py
i3visiotools/darkfy/__init__.py
i3visiotools/darkfy/darkfy-launcher.py
i3visiotools/darkfy/lib/__init__.py
i3visiotools/darkfy/lib/config_darkfy.py
i3visiotools/darkfy/lib/processing.py
i3visiotools/darkfy/lib/wrappers/__init__.py
i3visiotools/darkfy/lib/wrappers/ahmia.py
i3visiotools/darkfy/lib/wrappers/darkengine.py
i3visiotools/darkfy/lib/wrappers/torsearch.py
i3visiotools/wrappers/__init__.py
i3visiotools/wrappers/adtriboo.py
i3visiotools/wrappers/anarchy101.py
i3visiotools/wrappers/aporrealos.py
i3visiotools/wrappers/apsense.py
i3visiotools/wrappers/arduino.py
i3visiotools/wrappers/ariva.py
i3visiotools/wrappers/armorgames.py
i3visiotools/wrappers/artbreak.py
i3visiotools/wrappers/artician.py
i3visiotools/wrappers/arto.py
i3visiotools/wrappers/askfm.py
i3visiotools/wrappers/audiob.py
i3visiotools/wrappers/audioboo.py
i3visiotools/wrappers/authorstream.py
i3visiotools/wrappers/autospies.py
i3visiotools/wrappers/backyardchickens.py
i3visiotools/wrappers/badoo.py
i3visiotools/wrappers/behance.py
i3visiotools/wrappers/bennugd.py
i3visiotools/wrappers/bitbucket.py
i3visiotools/wrappers/bitcointalk.py
i3visiotools/wrappers/bitly.py
i3visiotools/wrappers/blackplanet.py
i3visiotools/wrappers/bladna.py
i3visiotools/wrappers/blip.py
i3visiotools/wrappers/blogspot.py
i3visiotools/wrappers/bookmarky.py
i3visiotools/wrappers/bookofmatches.py
i3visiotools/wrappers/boonex.py
i3visiotools/wrappers/bordom.py
i3visiotools/wrappers/boxedup.py
i3visiotools/wrappers/breakcom.py
i3visiotools/wrappers/bucketlistly.py
i3visiotools/wrappers/burbuja.py
