Metadata-Version: 1.0
Name: i3visiotools
Version: v0.2.0
Summary: i3visiotools - Set of common tools shared by i3visio apps and libraries.
Home-page: http://github.com/i3visio/i3visiotools
Author: Felix Brezo and Yaiza Rubio
Author-email: contacto@i3visio.com
License: COPYING
Platform: UNKNOWN
